simpleemailbot/__init__.py
simpleemailbot/simpleemailbot.py
SimpleEmailBot-0.0.1.dist-info/LICENSE
SimpleEmailBot-0.0.1.dist-info/METADATA
SimpleEmailBot-0.0.1.dist-info/WHEEL
SimpleEmailBot-0.0.1.dist-info/top_level.txt
SimpleEmailBot-0.0.1.dist-info/RECORD
