Metadata-Version: 2.1
Name: SimpleEmailBot
Version: 0.0.1
Summary: Simple package to email you when scripts are finished.
Home-page: https://github.com/cdmacfadyen/emailbot
Author: Craig Macfadyen
Author-email: cdmacfadyen@gmail.com
License: UNKNOWN
Keywords: email,simple
Platform: UNKNOWN
Classifier: Development Status :: 4 - Beta
Classifier: Intended Audience :: Developers
Classifier: License :: OSI Approved :: MIT License
Classifier: Programming Language :: Python :: 3
